[
  {
    "code": "FAD1018",
    "name": "TALLER INTERNACIONAL EUROPA",
    "credits": 10,
    "references": [
      ""
    ]
  },
  {
    "code": "ART9144",
    "name": "TALLER DE ARTE Y ELECTRÓNICA",
    "credits": 4,
    "references": [
      ""
    ]
  },
  {
    "code": "CIG1002",
    "name": "INGLÉS GENERAL II",
    "credits": 5,
    "references": [
      "ENG2100",
      "IAE3621",
      "IFM2303",
      "CI"
    ]
  },
  {
    "code": "CIG1003",
    "name": "INGLÉS GENERAL III",
    "credits": 5,
    "references": [
      "ENG2500",
      "IAE3721",
      "ICO8703",
      "CI"
    ]
  },
  {
    "code": "ART2121",
    "name": "TALLER CENTRAL II",
    "credits": 8,
    "references": [
      ""
    ]
  },
  {
    "code": "ART2122",
    "name": "ESCULTURA II",
    "credits": 5,
    "references": [
      ""
    ]
  },
  {
    "code": "ART2123",
    "name": "DIBUJO II",
    "credits": 5,
    "references": [
      ""
    ]
  },
  {
    "code": "ART2124",
    "name": "IMAGEN TÉCNICA",
    "credits": 5,
    "references": [
      "ART1051"
    ]
  },
  {
    "code": "ART2125",
    "name": "CULTURA VISUAL I",
    "credits": 4,
    "references": [
      ""
    ]
  },
  {
    "code": "ART2221",
    "name": "TALLER CENTRAL IV",
    "credits": 8,
    "references": [
      ""
    ]
  },
  {
    "code": "ART2222",
    "name": "PINTURA II",
    "credits": 5,
    "references": [
      ""
    ]
  },
  {
    "code": "ART2223",
    "name": "GESTIÓN DE PROYECTOS ARTÍSTICOS",
    "credits": 5,
    "references": [
      ""
    ]
  },
  {
    "code": "ART2224",
    "name": "SEMIÓTICA VISUAL",
    "credits": 4,
    "references": [
      "ART1056"
    ]
  },
  {
    "code": "ART2321",
    "name": "TALLER CENTRAL VI",
    "credits": 8,
    "references": [
      "ART1033"
    ]
  },
  {
    "code": "ART2324",
    "name": "ARTE CONTEMPORÁNEO EN CHILE",
    "credits": 5,
    "references": [
      "ART1060"
    ]
  },
  {
    "code": "ART2412",
    "name": "PASANTÍA",
    "credits": 8,
    "references": [
      "ART1048"
    ]
  },
  {
    "code": "ART2421",
    "name": "SEMINARIO DE GRADO",
    "credits": 22,
    "references": [
      "ART1041"
    ]
  },
  {
    "code": "ART2422",
    "name": "SEMINARIO DE MEMORIA",
    "credits": 8,
    "references": [
      ""
    ]
  },
  {
    "code": "CIG1014",
    "name": "INGLÉS GENERAL III",
    "credits": 5,
    "references": [
      "ICG3573"
    ]
  },
  {
    "code": "ART9148",
    "name": "RETÓRICAS DE LA PINTURA",
    "credits": 6,
    "references": [
      ""
    ]
  },
  {
    "code": "ART9151",
    "name": "IMAGEN EN MOVIMIENTO",
    "credits": 6,
    "references": [
      ""
    ]
  },
  {
    "code": "ART9166",
    "name": "LABORATORIO DE NARRATIVAS VISUALES",
    "credits": 6,
    "references": [
      ""
    ]
  },
  {
    "code": "ART9167",
    "name": "TALLER DE EXPOSICIONES INTERDISCIPLINAR",
    "credits": 6,
    "references": [
      ""
    ]
  }
]